{
 "cells": [
  {
   "cell_type": "code",
   "execution_count": 1,
   "metadata": {},
   "outputs": [],
   "source": [
    "def hello():\n",
    "    print(\"Hello, world!\")"
   ]
  },
  {
   "cell_type": "code",
   "execution_count": 2,
   "metadata": {},
   "outputs": [
    {
     "name": "stdout",
     "output_type": "stream",
     "text": [
      "Hello, world!\n"
     ]
    }
   ],
   "source": [
    "hello()"
   ]
  },
  {
   "cell_type": "code",
   "execution_count": 3,
   "metadata": {},
   "outputs": [],
   "source": [
    "import dis"
   ]
  },
  {
   "cell_type": "code",
   "execution_count": 4,
   "metadata": {},
   "outputs": [
    {
     "name": "stdout",
     "output_type": "stream",
     "text": [
      "  2           0 LOAD_GLOBAL              0 (print)\n",
      "              2 LOAD_CONST               1 ('Hello, world!')\n",
      "              4 CALL_FUNCTION            1\n",
      "              6 POP_TOP\n",
      "              8 LOAD_CONST               0 (None)\n",
      "             10 RETURN_VALUE\n"
     ]
    }
   ],
   "source": [
    "dis.dis(hello)"
   ]
  },
  {
   "cell_type": "code",
   "execution_count": 6,
   "metadata": {},
   "outputs": [],
   "source": [
    "def add(x,y):\n",
    "    return x + y"
   ]
  },
  {
   "cell_type": "code",
   "execution_count": 8,
   "metadata": {},
   "outputs": [
    {
     "name": "stdout",
     "output_type": "stream",
     "text": [
      "  2           0 LOAD_FAST                0 (x)\n",
      "              2 LOAD_FAST                1 (y)\n",
      "              4 BINARY_ADD\n",
      "              6 RETURN_VALUE\n"
     ]
    }
   ],
   "source": [
    "dis.dis(add)"
   ]
  },
  {
   "cell_type": "code",
   "execution_count": 9,
   "metadata": {},
   "outputs": [],
   "source": [
    "def mult(x,y):\n",
    "    res = 0\n",
    "    for i in range(y):\n",
    "        res += x\n",
    "    return res"
   ]
  },
  {
   "cell_type": "code",
   "execution_count": 10,
   "metadata": {},
   "outputs": [
    {
     "name": "stdout",
     "output_type": "stream",
     "text": [
      "  2           0 LOAD_CONST               1 (0)\n",
      "              2 STORE_FAST               2 (res)\n",
      "\n",
      "  3           4 SETUP_LOOP              24 (to 30)\n",
      "              6 LOAD_GLOBAL              0 (range)\n",
      "              8 LOAD_FAST                1 (y)\n",
      "             10 CALL_FUNCTION            1\n",
      "             12 GET_ITER\n",
      "        >>   14 FOR_ITER                12 (to 28)\n",
      "             16 STORE_FAST               3 (i)\n",
      "\n",
      "  4          18 LOAD_FAST                2 (res)\n",
      "             20 LOAD_FAST                0 (x)\n",
      "             22 INPLACE_ADD\n",
      "             24 STORE_FAST               2 (res)\n",
      "             26 JUMP_ABSOLUTE           14\n",
      "        >>   28 POP_BLOCK\n",
      "\n",
      "  5     >>   30 LOAD_FAST                2 (res)\n",
      "             32 RETURN_VALUE\n"
     ]
    }
   ],
   "source": [
    "dis.dis(mult)"
   ]
  },
  {
   "cell_type": "code",
   "execution_count": null,
   "metadata": {},
   "outputs": [],
   "source": []
  }
 ],
 "metadata": {
  "kernelspec": {
   "display_name": "Python 3",
   "language": "python",
   "name": "python3"
  },
  "language_info": {
   "codemirror_mode": {
    "name": "ipython",
    "version": 3
   },
   "file_extension": ".py",
   "mimetype": "text/x-python",
   "name": "python",
   "nbconvert_exporter": "python",
   "pygments_lexer": "ipython3",
   "version": "3.7.5"
  }
 },
 "nbformat": 4,
 "nbformat_minor": 2
}
